main/__init__.py
main/main.py
main/lib/Argument.py
main/lib/Command_help.py
main/lib/Description.py
main/lib/Helper.py
main/lib/Show_details.py
main/lib/Validate.py
main/lib/Where_locate.py
main/lib/__init__.py
linuxmedia-0.1.0.dist-info/METADATA
linuxmedia-0.1.0.dist-info/WHEEL
linuxmedia-0.1.0.dist-info/entry_points.txt
linuxmedia-0.1.0.dist-info/top_level.txt
linuxmedia-0.1.0.dist-info/RECORD
